{
  "version": 2.12,
  "blueprint_id": "2dcfa11c-518c-459b-bbe2-3951009deccd",
  "name": "Simple Card",
  "layout_size": "63.5, 88.9",
  "layout_grid_size": "0.08098987, 0.08098987",
  "main_panel_id": "00000000-0000-0000-0000-000000000000",
  "front_layers": [
    {
      "layer_id": "f7e91e32-3cd2-4388-8aff-d8c347aa1c24",
      "name": "Border",
      "padding": 0.0,
      "spacing": 0.0,
      "panels": [
        {
          "panel_id": "29931b48-c075-4825-866d-bf32be21c17b",
          "name": "",
          "enabled": true,
          "locked": true,
          "rotation": 0,
          "padding": "0, 0, 0, 0",
          "material_name": "Blank",
          "material_selection": 0,
          "material_tint": "#00000000",
          "anchor_min": "0, 0",
          "anchor_min_render": "0, 0",
          "anchor_max": "1, 1",
          "anchor_max_render": "1, 1",
          "type": "image",
          "data": {
            "uri": "",
            "mask_uri": "",
            "fit_mode": "fit",
            "zoom": 1.0,
            "offset": "0, 0",
            "tint": "#292A30FF"
          },
          "sort_mode": "0",
          "split_mode": "none",
          "parent_panel_id": "00000000-0000-0000-0000-000000000000"
        }
      ]
    },
    {
      "layer_id": "d18cded0-25cd-4cde-9164-586656495a03",
      "name": "Background",
      "padding": 0.0472440943,
      "spacing": 0.0,
      "panels": [
        {
          "panel_id": "c1c9e9a3-b878-4bf0-91dc-e2fbf4f3bde3",
          "name": "",
          "enabled": true,
          "locked": true,
          "rotation": 0,
          "padding": "0, 0, 0, 0",
          "material_name": "Blank",
          "material_selection": 0,
          "material_tint": "#00000000",
          "anchor_min": "0, 0",
          "anchor_min_render": "0, 0",
          "anchor_max": "1, 1",
          "anchor_max_render": "1, 1",
          "type": "image",
          "data": {
            "uri": "",
            "mask_uri": "",
            "fit_mode": "fit",
            "zoom": 1.0,
            "offset": "0, 0",
            "tint": "#E1E7F2FF"
          },
          "sort_mode": "1",
          "split_mode": "none",
          "parent_panel_id": "00000000-0000-0000-0000-000000000000"
        }
      ]
    },
    {
      "layer_id": "d1b52e24-946a-4cfa-8006-e519ff253e85",
      "name": "Illustration",
      "padding": 0.0472440943,
      "spacing": 0.0,
      "panels": [
        {
          "panel_id": "faf0a482-02ed-4e49-a2a9-f23d62a9580e",
          "name": "Illustration",
          "enabled": true,
          "locked": false,
          "rotation": 0,
          "padding": "0, 0, 0, 0",
          "material_name": "Blank",
          "material_selection": 0,
          "material_tint": "#00000000",
          "anchor_min": "0, 0",
          "anchor_min_render": "0, 0",
          "anchor_max": "1, 1",
          "anchor_max_render": "1, 1",
          "type": "image",
          "data": {
            "uri": "%PROJECT%/DefaultCardFront.png",
            "mask_uri": "",
            "fit_mode": "stretch",
            "zoom": 1.0,
            "offset": "0, 0",
            "tint": "#FFFFFFFF"
          },
          "sort_mode": "2",
          "split_mode": "none",
          "parent_panel_id": "00000000-0000-0000-0000-000000000000"
        }
      ]
    },
    {
      "layer_id": "40ec4205-425d-4d96-978a-16a04bb29c3b",
      "name": "MainContainers",
      "padding": 0.0472440943,
      "spacing": 0.0,
      "panels": [
        {
          "panel_id": "cc2b6377-4ac1-4f84-88cf-2d61735137c6",
          "name": "",
          "enabled": true,
          "locked": false,
          "rotation": 0,
          "padding": "0, 0, 0, 0",
          "material_name": "Blank",
          "material_selection": 0,
          "material_tint": "#00000000",
          "anchor_min": "0, 0",
          "anchor_min_render": "0, 0",
          "anchor_max": "1, 0.8557077",
          "anchor_max_render": "1, 0.8557077",
          "type": "image",
          "data": {
            "uri": "",
            "mask_uri": "",
            "fit_mode": "fit",
            "zoom": 1.1,
            "offset": "0, 0",
            "tint": "#FFFFFFFF"
          },
          "sort_mode": "2",
          "split_mode": "horizontal",
          "parent_panel_id": "00000000-0000-0000-0000-000000000000"
        },
        {
          "panel_id": "00f8c18b-54b9-4798-8b98-04609ba0246a",
          "name": "",
          "enabled": true,
          "locked": false,
          "rotation": 0,
          "padding": "0, 0, 0, 0",
          "material_name": "Blank",
          "material_selection": 0,
          "material_tint": "#00000000",
          "anchor_min": "0, 0",
          "anchor_min_render": "0, 0",
          "anchor_max": "0.2169922, 1",
          "anchor_max_render": "0.2169922, 0.8557077",
          "type": "icon",
          "data": {
            "uri": "/",
            "color_tint": "#424242FF",
            "color_background": "#00000000"
          },
          "sort_mode": "2",
          "split_mode": "vertical",
          "parent_panel_id": "cc2b6377-4ac1-4f84-88cf-2d61735137c6"
        },
        {
          "panel_id": "b05e7fc4-c10c-491d-a274-38f6ec036802",
          "name": "",
          "enabled": true,
          "locked": false,
          "rotation": 0,
          "padding": "0, 0, 0, 0",
          "material_name": "Blank",
          "material_selection": 0,
          "material_tint": "#00000000",
          "anchor_min": "0, 0",
          "anchor_min_render": "0, 3.755456E-08",
          "anchor_max": "1, 0.8136876",
          "anchor_max_render": "0.2169922, 0.6962788",
          "type": "icon",
          "data": {
            "uri": "/",
            "color_tint": "#424242FF",
            "color_background": "#00000000"
          },
          "sort_mode": "3",
          "split_mode": "horizontal",
          "parent_panel_id": "00f8c18b-54b9-4798-8b98-04609ba0246a"
        },
        {
          "panel_id": "c4cdf7bf-7f67-48e8-a4fa-f8f8a9b72d52",
          "name": "Deploy Cost",
          "enabled": true,
          "locked": true,
          "rotation": 0,
          "padding": "0, 0, 0.08, 0",
          "material_name": "Blank",
          "material_selection": 0,
          "material_tint": "#00000000",
          "anchor_min": "0, 0.8136876",
          "anchor_min_render": "0, 0.6962788",
          "anchor_max": "1, 1",
          "anchor_max_render": "0.2169922, 0.8557076",
          "type": "icon",
          "data": {
            "uri": "Abstract/spikes-full",
            "color_tint": "#FFFFFFFF",
            "color_background": "#00000000"
          },
          "sort_mode": "4",
          "split_mode": "horizontal",
          "parent_panel_id": "00f8c18b-54b9-4798-8b98-04609ba0246a"
        },
        {
          "panel_id": "7c70964a-582b-43b7-a7a0-c1a82d3bac05",
          "name": "",
          "enabled": true,
          "locked": false,
          "rotation": 0,
          "padding": "0, 0, 0, 0",
          "material_name": "Blank",
          "material_selection": 0,
          "material_tint": "#00000000",
          "anchor_min": "0.2169922, 0",
          "anchor_min_render": "0.2169922, 0",
          "anchor_max": "1, 1",
          "anchor_max_render": "1, 0.8557077",
          "type": "none",
          "data": {},
          "sort_mode": "5",
          "split_mode": "vertical",
          "parent_panel_id": "cc2b6377-4ac1-4f84-88cf-2d61735137c6"
        },
        {
          "panel_id": "8644063d-af9e-4136-a75a-4f5178226f14",
          "name": "",
          "enabled": true,
          "locked": false,
          "rotation": 0,
          "padding": "0, 0, 0, 0",
          "material_name": "Blank",
          "material_selection": 0,
          "material_tint": "#00000000",
          "anchor_min": "0, 0.8557077",
          "anchor_min_render": "0, 0.8557077",
          "anchor_max": "1, 1",
          "anchor_max_render": "1, 0.9999999",
          "type": "text",
          "data": {
            "font_family": "",
            "font_preferred_size": 24,
            "line_spacing": 1.0,
            "text_anchor": "middlecenter",
            "text": "{Abstract/square}",
            "color": "#141414FF",
            "outline_length": 1.0,
            "outline_color": "#FFFFFF00",
            "image_scaling": 1.0,
            "image_offset": "0, 0"
          },
          "sort_mode": "3",
          "split_mode": "horizontal",
          "parent_panel_id": "00000000-0000-0000-0000-000000000000"
        },
        {
          "panel_id": "45cd68c0-e030-43ee-b133-1994530eeadb",
          "name": "Element Color",
          "enabled": true,
          "locked": false,
          "rotation": 0,
          "padding": "0, 0, 0, 0",
          "material_name": "Blank",
          "material_selection": 0,
          "material_tint": "#00000000",
          "anchor_min": "0, 0",
          "anchor_min_render": "0, 0.8557077",
          "anchor_max": "0.2155282, 1",
          "anchor_max_render": "0.2155282, 0.9999999",
          "type": "icon",
          "data": {
            "uri": "Abstract/plain-circle",
            "color_tint": "#FF0000FF",
            "color_background": "#42424200"
          },
          "sort_mode": "6",
          "split_mode": "vertical",
          "parent_panel_id": "8644063d-af9e-4136-a75a-4f5178226f14"
        },
        {
          "panel_id": "97cea57f-47f3-4bd9-aac4-818236f213c3",
          "name": "",
          "enabled": true,
          "locked": true,
          "rotation": 0,
          "padding": "0, 0, 0.32, 0",
          "material_name": "Blank",
          "material_selection": 0,
          "material_tint": "#00000000",
          "anchor_min": "0.2155282, 0",
          "anchor_min_render": "0.2155282, 0.8557077",
          "anchor_max": "0.2169922, 1",
          "anchor_max_render": "0.2169922, 0.9999999",
          "type": "none",
          "data": {},
          "sort_mode": "7",
          "split_mode": "vertical",
          "parent_panel_id": "8644063d-af9e-4136-a75a-4f5178226f14"
        },
        {
          "panel_id": "92d8b21b-1eab-4abc-a48c-8ae705342db1",
          "name": "Name",
          "enabled": true,
          "locked": true,
          "rotation": 0,
          "padding": "0.24, 0, 0.24, 0",
          "material_name": "Blank",
          "material_selection": 0,
          "material_tint": "#00000000",
          "anchor_min": "0.2169922, 0",
          "anchor_min_render": "0.2169922, 0.8557077",
          "anchor_max": "1, 1",
          "anchor_max_render": "1, 0.9999999",
          "type": "image",
          "data": {
            "uri": "%PROJECT%/mainMenuGradient.png",
            "mask_uri": "",
            "fit_mode": "stretch",
            "zoom": 1.0,
            "offset": "0, 0",
            "tint": "#FFFFFFC9"
          },
          "sort_mode": "8",
          "split_mode": "vertical",
          "parent_panel_id": "8644063d-af9e-4136-a75a-4f5178226f14"
        }
      ]
    },
    {
      "layer_id": "42cc5f0f-dcea-4071-b8b9-89d12b505c44",
      "name": "EffectContainers",
      "padding": 0.0,
      "spacing": 0.0157480314,
      "panels": [
        {
          "panel_id": "3038da3d-597c-4d75-9d06-e9700e16d077",
          "name": "ID",
          "enabled": true,
          "locked": false,
          "rotation": 0,
          "padding": "0.08, 0.04, 0.42, 0",
          "material_name": "Blank",
          "material_selection": 0,
          "material_tint": "#00000000",
          "anchor_min": "0, 0",
          "anchor_min_render": "0, 3.628725E-08",
          "anchor_max": "1, 0.03686088",
          "anchor_max_render": "1, 0.03123661",
          "type": "none",
          "data": {},
          "sort_mode": "9",
          "split_mode": "horizontal",
          "parent_panel_id": "00000000-0000-0000-0000-000000000000"
        },
        {
          "panel_id": "d5151057-758f-4ecb-b8eb-9ca35d362f8f",
          "name": "",
          "enabled": true,
          "locked": false,
          "rotation": 0,
          "padding": "0, 0, 0, 0",
          "material_name": "Blank",
          "material_selection": 0,
          "material_tint": "#00000000",
          "anchor_min": "0, 0.03686088",
          "anchor_min_render": "0, 0.04248522",
          "anchor_max": "1, 0.3843002",
          "anchor_max_render": "1, 0.3786759",
          "type": "none",
          "data": {},
          "sort_mode": "47",
          "split_mode": "horizontal",
          "parent_panel_id": "00000000-0000-0000-0000-000000000000"
        },
        {
          "panel_id": "7dbdb1c1-14bc-46f4-8832-e17ca572d5af",
          "name": "",
          "enabled": true,
          "locked": false,
          "rotation": 0,
          "padding": "0, 0, 0, 0.16",
          "material_name": "Blank",
          "material_selection": 0,
          "material_tint": "#00000000",
          "anchor_min": "0, 0",
          "anchor_min_render": "0, 0.04248522",
          "anchor_max": "0.1820868, 1",
          "anchor_max_render": "0.1742127, 0.3786759",
          "type": "icon",
          "data": {
            "uri": "Abstract/plain-circle",
            "color_tint": "#000000C7",
            "color_background": "#00000000"
          },
          "sort_mode": "48",
          "split_mode": "vertical",
          "parent_panel_id": "d5151057-758f-4ecb-b8eb-9ca35d362f8f"
        },
        {
          "panel_id": "9b0445d4-4a11-4085-bf2c-a0dfd8d4808a",
          "name": "",
          "enabled": true,
          "locked": false,
          "rotation": 0,
          "padding": "0, 0, 0, 0.2",
          "material_name": "Blank",
          "material_selection": 0,
          "material_tint": "#00000000",
          "anchor_min": "0, 0",
          "anchor_min_render": "0, 0.04248517",
          "anchor_max": "1, 0.3339854",
          "anchor_max_render": "0.1742127, 0.1528771",
          "type": "icon",
          "data": {
            "uri": "Abstract/plain-circle",
            "color_tint": "#000000C7",
            "color_background": "#00000000"
          },
          "sort_mode": "10",
          "split_mode": "horizontal",
          "parent_panel_id": "7dbdb1c1-14bc-46f4-8832-e17ca572d5af"
        },
        {
          "panel_id": "e8d7fdaa-c15c-430b-984e-8f12c036b313",
          "name": "",
          "enabled": true,
          "locked": false,
          "rotation": 0,
          "padding": "0, 0, 0, 0.2",
          "material_name": "Blank",
          "material_selection": 0,
          "material_tint": "#00000000",
          "anchor_min": "0, 0.3339854",
          "anchor_min_render": "0, 0.1566588",
          "anchor_max": "1, 0.6669926",
          "anchor_max_render": "0.1742127, 0.2648311",
          "type": "icon",
          "data": {
            "uri": "Abstract/plain-circle",
            "color_tint": "#000000C7",
            "color_background": "#00000000"
          },
          "sort_mode": "11",
          "split_mode": "horizontal",
          "parent_panel_id": "7dbdb1c1-14bc-46f4-8832-e17ca572d5af"
        },
        {
          "panel_id": "fe88a5e3-9c50-451e-b2f5-58f34adc1e1c",
          "name": "",
          "enabled": true,
          "locked": false,
          "rotation": 0,
          "padding": "0, 0, 0, 0.16",
          "material_name": "Blank",
          "material_selection": 0,
          "material_tint": "#00000000",
          "anchor_min": "0, 0.6669926",
          "anchor_min_render": "0, 0.2686127",
          "anchor_max": "1, 0.8334963",
          "anchor_max_render": "0.1742127, 0.3208081",
          "type": "icon",
          "data": {
            "uri": "Abstract/plain-circle",
            "color_tint": "#000000C7",
            "color_background": "#00000000"
          },
          "sort_mode": "52",
          "split_mode": "horizontal",
          "parent_panel_id": "7dbdb1c1-14bc-46f4-8832-e17ca572d5af"
        },
        {
          "panel_id": "74c88ef2-4ab2-40bf-a6b6-efdeb075f5b9",
          "name": "",
          "enabled": true,
          "locked": false,
          "rotation": 0,
          "padding": "0, 0, 0, 0.16",
          "material_name": "Blank",
          "material_selection": 0,
          "material_tint": "#00000000",
          "anchor_min": "0, 0",
          "anchor_min_render": "0, 0.2686127",
          "anchor_max": "1, 1",
          "anchor_max_render": "0.1742127, 0.3208081",
          "type": "icon",
          "data": {
            "uri": "Abstract/plain-circle",
            "color_tint": "#000000C7",
            "color_background": "#00000000"
          },
          "sort_mode": "52",
          "split_mode": "vertical",
          "parent_panel_id": "fe88a5e3-9c50-451e-b2f5-58f34adc1e1c"
        },
        {
          "panel_id": "f25f7930-d2be-4d44-8ad5-c4b9524c09bb",
          "name": "",
          "enabled": true,
          "locked": false,
          "rotation": 0,
          "padding": "0, 0, 0, 0.5",
          "material_name": "Blank",
          "material_selection": 0,
          "material_tint": "#00000000",
          "anchor_min": "0, 0",
          "anchor_min_render": "0, 0.2686128",
          "anchor_max": "1, 1",
          "anchor_max_render": "0.1742127, 0.3205146",
          "type": "none",
          "data": {},
          "sort_mode": "13",
          "split_mode": "horizontal",
          "parent_panel_id": "74c88ef2-4ab2-40bf-a6b6-efdeb075f5b9"
        },
        {
          "panel_id": "db41fade-e5c0-428e-87f4-907eb7c91a87",
          "name": "",
          "enabled": true,
          "locked": false,
          "rotation": 0,
          "padding": "0, 0, 0, 0.16",
          "material_name": "Blank",
          "material_selection": 0,
          "material_tint": "#00000000",
          "anchor_min": "0, 1",
          "anchor_min_render": "0, 0.3211016",
          "anchor_max": "1, 1",
          "anchor_max_render": "0.1742127, 0.3208081",
          "type": "icon",
          "data": {
            "uri": "Abstract/plain-circle",
            "color_tint": "#000000C7",
            "color_background": "#00000000"
          },
          "sort_mode": "14",
          "split_mode": "horizontal",
          "parent_panel_id": "74c88ef2-4ab2-40bf-a6b6-efdeb075f5b9"
        },
        {
          "panel_id": "b32ebc75-3213-415e-83ca-50959a941872",
          "name": "",
          "enabled": true,
          "locked": false,
          "rotation": 0,
          "padding": "0, 0, 0, 0.16",
          "material_name": "Blank",
          "material_selection": 0,
          "material_tint": "#00000000",
          "anchor_min": "1, 0",
          "anchor_min_render": "0.1755845, 0.2686127",
          "anchor_max": "1, 1",
          "anchor_max_render": "0.1728409, 0.3208081",
          "type": "icon",
          "data": {
            "uri": "Abstract/plain-circle",
            "color_tint": "#000000C7",
            "color_background": "#00000000"
          },
          "sort_mode": "15",
          "split_mode": "vertical",
          "parent_panel_id": "fe88a5e3-9c50-451e-b2f5-58f34adc1e1c"
        },
        {
          "panel_id": "01b4264c-4fd5-4666-b68e-0612d55f71ed",
          "name": "",
          "enabled": true,
          "locked": false,
          "rotation": 0,
          "padding": "0, 0, 0, 0.5",
          "material_name": "Blank",
          "material_selection": 0,
          "material_tint": "#00000000",
          "anchor_min": "0, 0.8334963",
          "anchor_min_render": "0, 0.3245898",
          "anchor_max": "1, 1",
          "anchor_max_render": "0.1742127, 0.3786759",
          "type": "none",
          "data": {},
          "sort_mode": "16",
          "split_mode": "horizontal",
          "parent_panel_id": "7dbdb1c1-14bc-46f4-8832-e17ca572d5af"
        },
        {
          "panel_id": "60534713-6006-4a40-a506-28189dd97694",
          "name": "",
          "enabled": true,
          "locked": false,
          "rotation": 0,
          "padding": "0, 0.03, 0, 0",
          "material_name": "Blank",
          "material_selection": 0,
          "material_tint": "#00000000",
          "anchor_min": "0.1820868, 0",
          "anchor_min_render": "0.1899608, 0.04248522",
          "anchor_max": "1, 1",
          "anchor_max_render": "1, 0.3786759",
          "type": "image",
          "data": {
            "uri": "%PROJECT%/mainMenuGradient.png",
            "mask_uri": "",
            "fit_mode": "stretch",
            "zoom": 1.0,
            "offset": "0, 0",
            "tint": "#FFFFFFC9"
          },
          "sort_mode": "49",
          "split_mode": "vertical",
          "parent_panel_id": "d5151057-758f-4ecb-b8eb-9ca35d362f8f"
        },
        {
          "panel_id": "e59824c8-ba7a-4e21-9532-f01bfd178874",
          "name": "",
          "enabled": true,
          "locked": false,
          "rotation": 0,
          "padding": "0, 0.03, 0, 0",
          "material_name": "Blank",
          "material_selection": 0,
          "material_tint": "#00000000",
          "anchor_min": "0, 0",
          "anchor_min_render": "0.1899608, 0.04248521",
          "anchor_max": "1, 0.3284307",
          "anchor_max_render": "1, 0.1510097",
          "type": "image",
          "data": {
            "uri": "%PROJECT%/mainMenuGradient.png",
            "mask_uri": "",
            "fit_mode": "stretch",
            "zoom": 1.0,
            "offset": "0, 0",
            "tint": "#FFFFFFC9"
          },
          "sort_mode": "17",
          "split_mode": "horizontal",
          "parent_panel_id": "60534713-6006-4a40-a506-28189dd97694"
        },
        {
          "panel_id": "f914af00-eed9-4e3e-bce2-e706055163bb",
          "name": "",
          "enabled": true,
          "locked": false,
          "rotation": 0,
          "padding": "0, 0.03, 0, 0",
          "material_name": "Blank",
          "material_selection": 0,
          "material_tint": "#00000000",
          "anchor_min": "0, 0.3284307",
          "anchor_min_render": "0.1899608, 0.1547914",
          "anchor_max": "1, 0.6669926",
          "anchor_max_render": "1, 0.264831",
          "type": "image",
          "data": {
            "uri": "%PROJECT%/mainMenuGradient.png",
            "mask_uri": "",
            "fit_mode": "stretch",
            "zoom": 1.0,
            "offset": "0, 0",
            "tint": "#FFFFFFC9"
          },
          "sort_mode": "18",
          "split_mode": "horizontal",
          "parent_panel_id": "60534713-6006-4a40-a506-28189dd97694"
        },
        {
          "panel_id": "e423bfee-2273-4ec4-bbc1-eadb3321103e",
          "name": "",
          "enabled": true,
          "locked": false,
          "rotation": 0,
          "padding": "0, 0.03, 0, 0",
          "material_name": "Blank",
          "material_selection": 0,
          "material_tint": "#00000000",
          "anchor_min": "0, 0.6669926",
          "anchor_min_render": "0.1899608, 0.2686127",
          "anchor_max": "1, 1",
          "anchor_max_render": "1, 0.3786759",
          "type": "none",
          "data": {},
          "sort_mode": "19",
          "split_mode": "horizontal",
          "parent_panel_id": "60534713-6006-4a40-a506-28189dd97694"
        },
        {
          "panel_id": "76057029-7d19-49de-b4fd-4bdfe81a3f72",
          "name": "",
          "enabled": true,
          "locked": false,
          "rotation": 0,
          "padding": "0, 0, 0, 0",
          "material_name": "Blank",
          "material_selection": 0,
          "material_tint": "#00000000",
          "anchor_min": "0, 0.3843002",
          "anchor_min_render": "0, 0.3899245",
          "anchor_max": "1, 0.4042806",
          "anchor_max_render": "1, 0.3986563",
          "type": "none",
          "data": {},
          "sort_mode": "46",
          "split_mode": "horizontal",
          "parent_panel_id": "00000000-0000-0000-0000-000000000000"
        },
        {
          "panel_id": "2eee6152-e151-4a39-abea-a2f31b4d3689",
          "name": "",
          "enabled": true,
          "locked": false,
          "rotation": 0,
          "padding": "0, 0, 0, 0",
          "material_name": "Blank",
          "material_selection": 0,
          "material_tint": "#00000000",
          "anchor_min": "0, 0",
          "anchor_min_render": "0, 0.3899245",
          "anchor_max": "1, 1",
          "anchor_max_render": "1, 0.3986563",
          "type": "none",
          "data": {},
          "sort_mode": "21",
          "split_mode": "none",
          "parent_panel_id": "76057029-7d19-49de-b4fd-4bdfe81a3f72"
        },
        {
          "panel_id": "15ae220e-af2d-44c7-b26d-fe5cb3cd488e",
          "name": "",
          "enabled": true,
          "locked": false,
          "rotation": 0,
          "padding": "0, 0, 0, 0",
          "material_name": "Blank",
          "material_selection": 0,
          "material_tint": "#00000000",
          "anchor_min": "0, 0.4042806",
          "anchor_min_render": "0, 0.4099048",
          "anchor_max": "1, 1",
          "anchor_max_render": "1, 1",
          "type": "none",
          "data": {},
          "sort_mode": "22",
          "split_mode": "horizontal",
          "parent_panel_id": "00000000-0000-0000-0000-000000000000"
        }
      ]
    },
    {
      "layer_id": "f0627222-6c37-45fc-a0b1-d385210c668f",
      "name": "Effects",
      "padding": 0.0,
      "spacing": 0.0,
      "panels": [
        {
          "panel_id": "6b7e09f5-4bf5-475a-b56c-5318e39d4cff",
          "name": "",
          "enabled": true,
          "locked": false,
          "rotation": 0,
          "padding": "0, 0, 0, 0",
          "material_name": "Blank",
          "material_selection": 0,
          "material_tint": "#00000000",
          "anchor_min": "0, 0",
          "anchor_min_render": "0, 0",
          "anchor_max": "1, 0.03720067",
          "anchor_max_render": "1, 0.03720067",
          "type": "none",
          "data": {},
          "sort_mode": "23",
          "split_mode": "horizontal",
          "parent_panel_id": "00000000-0000-0000-0000-000000000000"
        },
        {
          "panel_id": "2518805c-4665-4086-9833-6d9d567a3696",
          "name": "",
          "enabled": true,
          "locked": false,
          "rotation": 0,
          "padding": "0, 0, 0, 0",
          "material_name": "Blank",
          "material_selection": 0,
          "material_tint": "#00000000",
          "anchor_min": "0, 0.03720067",
          "anchor_min_render": "0, 0.03720069",
          "anchor_max": "1, 0.1529005",
          "anchor_max_render": "1, 0.1529005",
          "type": "none",
          "data": {},
          "sort_mode": "77",
          "split_mode": "horizontal",
          "parent_panel_id": "00000000-0000-0000-0000-000000000000"
        },
        {
          "panel_id": "95d68930-2026-4fc4-8d56-690713c8781d",
          "name": "",
          "enabled": true,
          "locked": false,
          "rotation": 0,
          "padding": "0.15, 0.15, 0.15, 0.25",
          "material_name": "Blank",
          "material_selection": 0,
          "material_tint": "#00000000",
          "anchor_min": "0, 0",
          "anchor_min_render": "0, 0.03720069",
          "anchor_max": "0.1850394, 1",
          "anchor_max_render": "0.1850393, 0.1529005",
          "type": "icon",
          "data": {
            "uri": "Abstract/hospital-cross",
            "color_tint": "#FFFFFFFD",
            "color_background": "#00000000"
          },
          "sort_mode": "24",
          "split_mode": "vertical",
          "parent_panel_id": "2518805c-4665-4086-9833-6d9d567a3696"
        },
        {
          "panel_id": "e29eb4dc-58ea-4697-ba1b-c88a654d895a",
          "name": "",
          "enabled": true,
          "locked": false,
          "rotation": 0,
          "padding": "0.04, 0.04, 0.04, 0.04",
          "material_name": "Blank",
          "material_selection": 0,
          "material_tint": "#00000000",
          "anchor_min": "0.1850394, 0",
          "anchor_min_render": "0.1850394, 0.03720069",
          "anchor_max": "1, 1",
          "anchor_max_render": "1, 0.1529005",
          "type": "text",
          "data": {
            "font_family": "Noto Sans",
            "font_preferred_size": 16,
            "line_spacing": 1.0,
            "text_anchor": "middleleft",
            "text": "<b>Effect:</b> Sample effect\nAnother Line",
            "color": "#FFFFFFFF",
            "outline_length": 1.0,
            "outline_color": "#000000FF",
            "image_scaling": 1.0,
            "image_offset": "0, 0"
          },
          "sort_mode": "25",
          "split_mode": "vertical",
          "parent_panel_id": "2518805c-4665-4086-9833-6d9d567a3696"
        },
        {
          "panel_id": "b189ed89-2be8-40f3-9356-0fb023b9a022",
          "name": "",
          "enabled": true,
          "locked": false,
          "rotation": 0,
          "padding": "0, 0, 0, 0",
          "material_name": "Blank",
          "material_selection": 0,
          "material_tint": "#00000000",
          "anchor_min": "0, 0.1529005",
          "anchor_min_render": "0, 0.1529005",
          "anchor_max": "1, 0.2686003",
          "anchor_max_render": "1, 0.2686003",
          "type": "none",
          "data": {},
          "sort_mode": "74",
          "split_mode": "horizontal",
          "parent_panel_id": "00000000-0000-0000-0000-000000000000"
        },
        {
          "panel_id": "c34767c9-a1fa-435b-ac8a-c503c21d3eab",
          "name": "",
          "enabled": true,
          "locked": false,
          "rotation": 0,
          "padding": "0.15, 0.15, 0.15, 0.25",
          "material_name": "Blank",
          "material_selection": 0,
          "material_tint": "#00000000",
          "anchor_min": "0, 0",
          "anchor_min_render": "0, 0.1529005",
          "anchor_max": "0.1850394, 1",
          "anchor_max_render": "0.1850393, 0.2686003",
          "type": "icon",
          "data": {
            "uri": "Abstract/crossed-swords",
            "color_tint": "#FFFFFFFD",
            "color_background": "#00000000"
          },
          "sort_mode": "26",
          "split_mode": "vertical",
          "parent_panel_id": "b189ed89-2be8-40f3-9356-0fb023b9a022"
        },
        {
          "panel_id": "64490993-e22b-4f5e-8bad-5e7fd5543502",
          "name": "",
          "enabled": true,
          "locked": false,
          "rotation": 0,
          "padding": "0.04, 0.04, 0.04, 0.04",
          "material_name": "Blank",
          "material_selection": 0,
          "material_tint": "#00000000",
          "anchor_min": "0.1850394, 0",
          "anchor_min_render": "0.1850394, 0.1529005",
          "anchor_max": "1, 1",
          "anchor_max_render": "1, 0.2686003",
          "type": "text",
          "data": {
            "font_family": "Noto Sans",
            "font_preferred_size": 16,
            "line_spacing": 1.0,
            "text_anchor": "middleleft",
            "text": "<b>Effect:</b> Sample effect\nAnother Line",
            "color": "#FFFFFFFF",
            "outline_length": 1.0,
            "outline_color": "#000000FF",
            "image_scaling": 1.0,
            "image_offset": "0, 0"
          },
          "sort_mode": "28",
          "split_mode": "vertical",
          "parent_panel_id": "b189ed89-2be8-40f3-9356-0fb023b9a022"
        },
        {
          "panel_id": "3a9f3ec7-bf33-4306-81c7-17a176935b2b",
          "name": "",
          "enabled": true,
          "locked": false,
          "rotation": 0,
          "padding": "0, 0, 0, 0",
          "material_name": "Blank",
          "material_selection": 0,
          "material_tint": "#00000000",
          "anchor_min": "0, 0.2686003",
          "anchor_min_render": "0, 0.2686003",
          "anchor_max": "1, 0.3781213",
          "anchor_max_render": "1, 0.3781213",
          "type": "icon",
          "data": {
            "uri": "Abstract/embrassed-energy",
            "color_tint": "#FFFFFFFD",
            "color_background": "#00000000"
          },
          "sort_mode": "29",
          "split_mode": "horizontal",
          "parent_panel_id": "00000000-0000-0000-0000-000000000000"
        },
        {
          "panel_id": "49172947-6008-4f3e-b9e5-1d9b227af88e",
          "name": "",
          "enabled": true,
          "locked": false,
          "rotation": 0,
          "padding": "0, 0, 0, 0",
          "material_name": "Blank",
          "material_selection": 0,
          "material_tint": "#00000000",
          "anchor_min": "0, 0.3781213",
          "anchor_min_render": "0, 0.3781213",
          "anchor_max": "1, 1",
          "anchor_max_render": "1, 1",
          "type": "none",
          "data": {},
          "sort_mode": "30",
          "split_mode": "horizontal",
          "parent_panel_id": "00000000-0000-0000-0000-000000000000"
        }
      ]
    },
    {
      "layer_id": "349d1a93-2840-4e88-940c-a9f15f86d4e5",
      "name": "Main Data",
      "padding": 0.0472440943,
      "spacing": 0.0,
      "panels": [
        {
          "panel_id": "c03f2758-cdfe-471e-a0ad-ffd5a1142ed7",
          "name": "",
          "enabled": true,
          "locked": false,
          "rotation": 0,
          "padding": "0, 0, 0, 0",
          "material_name": "Blank",
          "material_selection": 0,
          "material_tint": "#00000000",
          "anchor_min": "0, 0",
          "anchor_min_render": "0, 0",
          "anchor_max": "1, 0.8557077",
          "anchor_max_render": "1, 0.8557077",
          "type": "image",
          "data": {
            "uri": "",
            "mask_uri": "",
            "fit_mode": "fit",
            "zoom": 1.1,
            "offset": "0, 0",
            "tint": "#FFFFFFFF"
          },
          "sort_mode": "2",
          "split_mode": "horizontal",
          "parent_panel_id": "00000000-0000-0000-0000-000000000000"
        },
        {
          "panel_id": "44431045-60b3-4851-a432-b306107060a3",
          "name": "",
          "enabled": true,
          "locked": false,
          "rotation": 0,
          "padding": "0, 0, 0, 0",
          "material_name": "Blank",
          "material_selection": 0,
          "material_tint": "#00000000",
          "anchor_min": "0, 0",
          "anchor_min_render": "0, 0",
          "anchor_max": "0.2169922, 1",
          "anchor_max_render": "0.2169922, 0.8557077",
          "type": "icon",
          "data": {
            "uri": "/",
            "color_tint": "#424242FF",
            "color_background": "#00000000"
          },
          "sort_mode": "2",
          "split_mode": "vertical",
          "parent_panel_id": "c03f2758-cdfe-471e-a0ad-ffd5a1142ed7"
        },
        {
          "panel_id": "2dc20e67-2b3a-4b7a-b114-d64331d8b01c",
          "name": "",
          "enabled": true,
          "locked": false,
          "rotation": 0,
          "padding": "0, 0, 0, 0",
          "material_name": "Blank",
          "material_selection": 0,
          "material_tint": "#00000000",
          "anchor_min": "0, 0",
          "anchor_min_render": "0, 0",
          "anchor_max": "1, 0.5065719",
          "anchor_max_render": "0.2169922, 0.4334774",
          "type": "none",
          "data": {},
          "sort_mode": "31",
          "split_mode": "horizontal",
          "parent_panel_id": "44431045-60b3-4851-a432-b306107060a3"
        },
        {
          "panel_id": "5e1280fd-fbf6-485c-a56d-27350a642490",
          "name": "",
          "enabled": true,
          "locked": false,
          "rotation": 0,
          "padding": "0, 0, 0, 0",
          "material_name": "Blank",
          "material_selection": 0,
          "material_tint": "#00000000",
          "anchor_min": "0, 0.5065719",
          "anchor_min_render": "0, 0.4334774",
          "anchor_max": "1, 0.817531",
          "anchor_max_render": "0.2169922, 0.6995675",
          "type": "icon",
          "data": {
            "uri": "/",
            "color_tint": "#424242FF",
            "color_background": "#00000000"
          },
          "sort_mode": "4",
          "split_mode": "horizontal",
          "parent_panel_id": "44431045-60b3-4851-a432-b306107060a3"
        },
        {
          "panel_id": "d2256305-eaee-4896-95b1-630a2b2fe104",
          "name": "",
          "enabled": true,
          "locked": false,
          "rotation": 0,
          "padding": "0, 0, 0, 0",
          "material_name": "Blank",
          "material_selection": 0,
          "material_tint": "#00000000",
          "anchor_min": "0, 0",
          "anchor_min_render": "0, 0.4334774",
          "anchor_max": "0.5168772, 1",
          "anchor_max_render": "0.1121583, 0.6995675",
          "type": "icon",
          "data": {
            "uri": "/",
            "color_tint": "#424242FF",
            "color_background": "#00000000"
          },
          "sort_mode": "4",
          "split_mode": "vertical",
          "parent_panel_id": "5e1280fd-fbf6-485c-a56d-27350a642490"
        },
        {
          "panel_id": "b2d23103-8537-4967-8726-d039f432431d",
          "name": "Mana4",
          "enabled": true,
          "locked": false,
          "rotation": 0,
          "padding": "0, 0, 0, 0",
          "material_name": "Blank",
          "material_selection": 0,
          "material_tint": "#00000000",
          "anchor_min": "0, 0",
          "anchor_min_render": "0, 0.4334775",
          "anchor_max": "1, 0.2499999",
          "anchor_max_render": "0.1121583, 0.4999999",
          "type": "icon",
          "data": {
            "uri": "Abstract/eclipse-flare",
            "color_tint": "#424242FF",
            "color_background": "#00000000"
          },
          "sort_mode": "27",
          "split_mode": "horizontal",
          "parent_panel_id": "d2256305-eaee-4896-95b1-630a2b2fe104"
        },
        {
          "panel_id": "d33eecf0-02de-4376-86c3-5bd6f06022a4",
          "name": "Mana3",
          "enabled": true,
          "locked": false,
          "rotation": 0,
          "padding": "0, 0, 0, 0",
          "material_name": "Blank",
          "material_selection": 0,
          "material_tint": "#00000000",
          "anchor_min": "0, 0.2499999",
          "anchor_min_render": "0, 0.5",
          "anchor_max": "1, 0.4999997",
          "anchor_max_render": "0.1121583, 0.5665224",
          "type": "icon",
          "data": {
            "uri": "Abstract/eclipse-flare",
            "color_tint": "#424242FF",
            "color_background": "#00000000"
          },
          "sort_mode": "20",
          "split_mode": "horizontal",
          "parent_panel_id": "d2256305-eaee-4896-95b1-630a2b2fe104"
        },
        {
          "panel_id": "35f30cf1-e1bd-4253-b895-958c4a3f9d71",
          "name": "Mana2",
          "enabled": true,
          "locked": false,
          "rotation": 0,
          "padding": "0, 0, 0, 0",
          "material_name": "Blank",
          "material_selection": 0,
          "material_tint": "#00000000",
          "anchor_min": "0, 0.4999997",
          "anchor_min_render": "0, 0.5665225",
          "anchor_max": "1, 0.7499998",
          "anchor_max_render": "0.1121583, 0.633045",
          "type": "icon",
          "data": {
            "uri": "Abstract/eclipse-flare",
            "color_tint": "#424242FF",
            "color_background": "#00000000"
          },
          "sort_mode": "12",
          "split_mode": "horizontal",
          "parent_panel_id": "d2256305-eaee-4896-95b1-630a2b2fe104"
        },
        {
          "panel_id": "cc39a9da-f594-4bdb-808c-82274dd7bcaf",
          "name": "Mana1",
          "enabled": true,
          "locked": false,
          "rotation": 0,
          "padding": "0, 0, 0, 0",
          "material_name": "Blank",
          "material_selection": 0,
          "material_tint": "#00000000",
          "anchor_min": "0, 0.7499998",
          "anchor_min_render": "0, 0.633045",
          "anchor_max": "1, 1",
          "anchor_max_render": "0.1121583, 0.6995675",
          "type": "icon",
          "data": {
            "uri": "Abstract/eclipse-flare",
            "color_tint": "#424242FF",
            "color_background": "#00000000"
          },
          "sort_mode": "32",
          "split_mode": "horizontal",
          "parent_panel_id": "d2256305-eaee-4896-95b1-630a2b2fe104"
        },
        {
          "panel_id": "a974335c-7910-4444-82c5-aa57d94bd67b",
          "name": "",
          "enabled": true,
          "locked": false,
          "rotation": 0,
          "padding": "0, 0, 0, 0",
          "material_name": "Blank",
          "material_selection": 0,
          "material_tint": "#00000000",
          "anchor_min": "0.5168772, 0",
          "anchor_min_render": "0.1121583, 0.4334774",
          "anchor_max": "1, 1",
          "anchor_max_render": "0.2169922, 0.6995675",
          "type": "icon",
          "data": {
            "uri": "/",
            "color_tint": "#424242FF",
            "color_background": "#00000000"
          },
          "sort_mode": "10",
          "split_mode": "vertical",
          "parent_panel_id": "5e1280fd-fbf6-485c-a56d-27350a642490"
        },
        {
          "panel_id": "f6abce2d-aef8-48ea-908f-5fa34a804427",
          "name": "Mana8",
          "enabled": true,
          "locked": false,
          "rotation": 0,
          "padding": "0, 0, 0, 0",
          "material_name": "Blank",
          "material_selection": 0,
          "material_tint": "#00000000",
          "anchor_min": "0, 0",
          "anchor_min_render": "0.1121583, 0.4334775",
          "anchor_max": "1, 0.2499999",
          "anchor_max_render": "0.2169922, 0.4999999",
          "type": "icon",
          "data": {
            "uri": "Abstract/eclipse-flare",
            "color_tint": "#424242FF",
            "color_background": "#00000000"
          },
          "sort_mode": "33",
          "split_mode": "horizontal",
          "parent_panel_id": "a974335c-7910-4444-82c5-aa57d94bd67b"
        },
        {
          "panel_id": "a1a91efa-71ed-4f6a-88a0-c0c6ad0ac33e",
          "name": "Mana7",
          "enabled": true,
          "locked": false,
          "rotation": 0,
          "padding": "0, 0, 0, 0",
          "material_name": "Blank",
          "material_selection": 0,
          "material_tint": "#00000000",
          "anchor_min": "0, 0.2499999",
          "anchor_min_render": "0.1121583, 0.5",
          "anchor_max": "1, 0.4999997",
          "anchor_max_render": "0.2169922, 0.5665224",
          "type": "icon",
          "data": {
            "uri": "Abstract/eclipse-flare",
            "color_tint": "#424242FF",
            "color_background": "#00000000"
          },
          "sort_mode": "35",
          "split_mode": "horizontal",
          "parent_panel_id": "a974335c-7910-4444-82c5-aa57d94bd67b"
        },
        {
          "panel_id": "a0c1bdf4-49f1-41e9-93f0-cb0995b231fc",
          "name": "Mana6",
          "enabled": true,
          "locked": false,
          "rotation": 0,
          "padding": "0, 0, 0, 0",
          "material_name": "Blank",
          "material_selection": 0,
          "material_tint": "#00000000",
          "anchor_min": "0, 0.4999997",
          "anchor_min_render": "0.1121583, 0.5665225",
          "anchor_max": "1, 0.7499998",
          "anchor_max_render": "0.2169922, 0.633045",
          "type": "icon",
          "data": {
            "uri": "Abstract/eclipse-flare",
            "color_tint": "#424242FF",
            "color_background": "#00000000"
          },
          "sort_mode": "36",
          "split_mode": "horizontal",
          "parent_panel_id": "a974335c-7910-4444-82c5-aa57d94bd67b"
        },
        {
          "panel_id": "bb06e056-b8e4-4bb9-afd5-c9ff62cfcd43",
          "name": "Mana5",
          "enabled": true,
          "locked": false,
          "rotation": 0,
          "padding": "0, 0, 0, 0",
          "material_name": "Blank",
          "material_selection": 0,
          "material_tint": "#00000000",
          "anchor_min": "0, 0.7499998",
          "anchor_min_render": "0.1121583, 0.633045",
          "anchor_max": "1, 1",
          "anchor_max_render": "0.2169922, 0.6995675",
          "type": "icon",
          "data": {
            "uri": "Abstract/eclipse-flare",
            "color_tint": "#424242FF",
            "color_background": "#00000000"
          },
          "sort_mode": "37",
          "split_mode": "horizontal",
          "parent_panel_id": "a974335c-7910-4444-82c5-aa57d94bd67b"
        },
        {
          "panel_id": "16bdf827-4489-4062-ba85-526a81cbc2ea",
          "name": "",
          "enabled": true,
          "locked": false,
          "rotation": 0,
          "padding": "0, 0, 0, 0",
          "material_name": "Blank",
          "material_selection": 0,
          "material_tint": "#00000000",
          "anchor_min": "0, 1",
          "anchor_min_render": "0.1121583, 0.6995676",
          "anchor_max": "1, 1",
          "anchor_max_render": "0.2169922, 0.6995676",
          "type": "icon",
          "data": {
            "uri": "/",
            "color_tint": "#424242FF",
            "color_background": "#00000000"
          },
          "sort_mode": "38",
          "split_mode": "horizontal",
          "parent_panel_id": "a974335c-7910-4444-82c5-aa57d94bd67b"
        },
        {
          "panel_id": "e1e54837-d9ac-433f-80e4-954209c5a2ff",
          "name": "",
          "enabled": true,
          "locked": false,
          "rotation": 0,
          "padding": "0, 0, 0, 0",
          "material_name": "Blank",
          "material_selection": 0,
          "material_tint": "#00000000",
          "anchor_min": "0, 1",
          "anchor_min_render": "0.1121583, 0.6995676",
          "anchor_max": "1, 1",
          "anchor_max_render": "0.2169922, 0.6995676",
          "type": "icon",
          "data": {
            "uri": "/",
            "color_tint": "#424242FF",
            "color_background": "#00000000"
          },
          "sort_mode": "34",
          "split_mode": "horizontal",
          "parent_panel_id": "a974335c-7910-4444-82c5-aa57d94bd67b"
        },
        {
          "panel_id": "657b60b8-715f-4f23-bc0f-43f94b0177bb",
          "name": "",
          "enabled": true,
          "locked": false,
          "rotation": 0,
          "padding": "0, 0, 0, 0",
          "material_name": "Blank",
          "material_selection": 0,
          "material_tint": "#00000000",
          "anchor_min": "0, 1",
          "anchor_min_render": "0.1121583, 0.6995676",
          "anchor_max": "1, 1",
          "anchor_max_render": "0.2169922, 0.6995676",
          "type": "icon",
          "data": {
            "uri": "/",
            "color_tint": "#424242FF",
            "color_background": "#00000000"
          },
          "sort_mode": "39",
          "split_mode": "horizontal",
          "parent_panel_id": "a974335c-7910-4444-82c5-aa57d94bd67b"
        },
        {
          "panel_id": "b7511444-0d2e-4016-857e-0c40794fc587",
          "name": "Deploy Cost",
          "enabled": true,
          "locked": false,
          "rotation": 0,
          "padding": "0.16, 0.3, 0.16, 0.3",
          "material_name": "Blank",
          "material_selection": 0,
          "material_tint": "#00000000",
          "anchor_min": "0, 0.817531",
          "anchor_min_render": "0, 0.6995676",
          "anchor_max": "1, 1",
          "anchor_max_render": "0.2169922, 0.8557077",
          "type": "text",
          "data": {
            "font_family": "Ubuntu",
            "font_preferred_size": 36,
            "line_spacing": 1.0,
            "text_anchor": "middlecenter",
            "text": "3",
            "color": "#FFFFFFFF",
            "outline_length": 5.0,
            "outline_color": "#000000FF",
            "image_scaling": 1.0,
            "image_offset": "0, 0"
          },
          "sort_mode": "40",
          "split_mode": "horizontal",
          "parent_panel_id": "44431045-60b3-4851-a432-b306107060a3"
        },
        {
          "panel_id": "eae81dab-589d-42a4-8ca1-ed19a7d70475",
          "name": "",
          "enabled": true,
          "locked": false,
          "rotation": 0,
          "padding": "0, 0, 0, 0",
          "material_name": "Blank",
          "material_selection": 0,
          "material_tint": "#00000000",
          "anchor_min": "0.2169922, 0",
          "anchor_min_render": "0.2169922, 0",
          "anchor_max": "1, 1",
          "anchor_max_render": "1, 0.8557077",
          "type": "none",
          "data": {},
          "sort_mode": "29",
          "split_mode": "vertical",
          "parent_panel_id": "c03f2758-cdfe-471e-a0ad-ffd5a1142ed7"
        },
        {
          "panel_id": "3bc065e3-e8f5-4ea9-a0bc-40796b13ca6e",
          "name": "",
          "enabled": true,
          "locked": false,
          "rotation": 0,
          "padding": "0, 0.04, 0, 0",
          "material_name": "Blank",
          "material_selection": 0,
          "material_tint": "#00000000",
          "anchor_min": "0, 0",
          "anchor_min_render": "0.2169922, -1.877728E-08",
          "anchor_max": "1, 0.02561231",
          "anchor_max_render": "1, 0.0219166",
          "type": "text",
          "data": {
            "font_family": "Ubuntu",
            "font_preferred_size": 8,
            "line_spacing": 1.0,
            "text_anchor": "middleright",
            "text": "TEST-001-00",
            "color": "#FFFFFFFF",
            "outline_length": 1.0,
            "outline_color": "#000000FF",
            "image_scaling": 1.0,
            "image_offset": "0, 0"
          },
          "sort_mode": "41",
          "split_mode": "horizontal",
          "parent_panel_id": "eae81dab-589d-42a4-8ca1-ed19a7d70475"
        },
        {
          "panel_id": "f776f339-35db-4acf-815a-78ac730bb791",
          "name": "",
          "enabled": true,
          "locked": false,
          "rotation": 0,
          "padding": "0, 0, 0, 0",
          "material_name": "Blank",
          "material_selection": 0,
          "material_tint": "#00000000",
          "anchor_min": "0, 0.02561231",
          "anchor_min_render": "0.2169922, 0.02191665",
          "anchor_max": "1, 1",
          "anchor_max_render": "1, 0.8557077",
          "type": "none",
          "data": {},
          "sort_mode": "42",
          "split_mode": "horizontal",
          "parent_panel_id": "eae81dab-589d-42a4-8ca1-ed19a7d70475"
        },
        {
          "panel_id": "321a4d7b-e998-4679-8861-99d2addb220c",
          "name": "",
          "enabled": true,
          "locked": false,
          "rotation": 0,
          "padding": "0, 0, 0, 0",
          "material_name": "Blank",
          "material_selection": 0,
          "material_tint": "#00000000",
          "anchor_min": "0, 0.8557077",
          "anchor_min_render": "0, 0.8557077",
          "anchor_max": "1, 1",
          "anchor_max_render": "1, 0.9999999",
          "type": "text",
          "data": {
            "font_family": "",
            "font_preferred_size": 24,
            "line_spacing": 1.0,
            "text_anchor": "middlecenter",
            "text": "{Abstract/square}",
            "color": "#141414FF",
            "outline_length": 1.0,
            "outline_color": "#FFFFFF00",
            "image_scaling": 1.0,
            "image_offset": "0, 0"
          },
          "sort_mode": "3",
          "split_mode": "horizontal",
          "parent_panel_id": "00000000-0000-0000-0000-000000000000"
        },
        {
          "panel_id": "21db9090-1380-4414-9f16-e26f3ed611e5",
          "name": "Element",
          "enabled": true,
          "locked": false,
          "rotation": 0,
          "padding": "0.16, 0.16, 0.16, 0.16",
          "material_name": "Blank",
          "material_selection": 0,
          "material_tint": "#00000000",
          "anchor_min": "0, 0",
          "anchor_min_render": "0, 0.8557077",
          "anchor_max": "0.2155282, 1",
          "anchor_max_render": "0.2155282, 0.9999999",
          "type": "icon",
          "data": {
            "uri": "Nature/fire",
            "color_tint": "#FFFFFFFF",
            "color_background": "#FFFFFF00"
          },
          "sort_mode": "43",
          "split_mode": "vertical",
          "parent_panel_id": "321a4d7b-e998-4679-8861-99d2addb220c"
        },
        {
          "panel_id": "fe32ec5c-083f-4ca4-a307-976fc66989c5",
          "name": "Faction",
          "enabled": true,
          "locked": false,
          "rotation": 0,
          "padding": "0.13, 0.09, 0.44, 0.08",
          "material_name": "Blank",
          "material_selection": 0,
          "material_tint": "#00000000",
          "anchor_min": "0.2155282, 0",
          "anchor_min_render": "0.2155282, 0.8557077",
          "anchor_max": "0.2204866, 1",
          "anchor_max_render": "0.2204866, 0.9999999",
          "type": "none",
          "data": {},
          "sort_mode": "45",
          "split_mode": "vertical",
          "parent_panel_id": "321a4d7b-e998-4679-8861-99d2addb220c"
        },
        {
          "panel_id": "b3330089-81d6-426e-bbe1-3b2eb9fa9d79",
          "name": "Name",
          "enabled": true,
          "locked": false,
          "rotation": 0,
          "padding": "0.24, 0.04, 0.24, 0",
          "material_name": "Blank",
          "material_selection": 0,
          "material_tint": "#00000000",
          "anchor_min": "0.2204866, 0",
          "anchor_min_render": "0.2204866, 0.8557077",
          "anchor_max": "1, 1",
          "anchor_max_render": "1, 0.9999999",
          "type": "text",
          "data": {
            "font_family": "Raleway",
            "font_preferred_size": 24,
            "line_spacing": 1.0,
            "text_anchor": "middleright",
            "text": "<b>Sample Text</b>",
            "color": "#FFFFFFFF",
            "outline_length": 1.0,
            "outline_color": "#000000FF",
            "image_scaling": 1.0,
            "image_offset": "0, 0"
          },
          "sort_mode": "46",
          "split_mode": "vertical",
          "parent_panel_id": "321a4d7b-e998-4679-8861-99d2addb220c"
        }
      ]
    }
  ],
  "back_layers": [
    {
      "layer_id": "637b7c98-9ec1-4270-85de-84d412b56c9f",
      "name": "Layer 01 Back",
      "padding": 2.638507E-05,
      "spacing": 0.025,
      "panels": [
        {
          "panel_id": "20b4f3c0-71e2-4604-9edb-792bc994fb8d",
          "name": "",
          "enabled": true,
          "locked": false,
          "rotation": 0,
          "padding": "0, 0, 0, 0",
          "material_name": "Blank",
          "material_selection": 0,
          "material_tint": "#00000000",
          "anchor_min": "0, 0",
          "anchor_min_render": "0, 0",
          "anchor_max": "1, 1",
          "anchor_max_render": "1, 1",
          "type": "image",
          "data": {
            "uri": "%PROJECT%/DefaultCardBack.png",
            "mask_uri": "",
            "fit_mode": "fit",
            "zoom": 1.0,
            "offset": "0, 0",
            "tint": "#FFFFFFFF"
          },
          "sort_mode": "44",
          "split_mode": "none",
          "parent_panel_id": "00000000-0000-0000-0000-000000000000"
        }
      ]
    }
  ]
}